diff_module.v
module diff_module #(
    parameter WINDOW_SIZE_BITS = 8,
    parameter DATA_WIDTH = 16,
    parameter MAX_TAU = 40 // representa 20ms
) (
    input clk,
    output reg [15:0] address,
    input wire [15:0] initial_address,
    input wire [DATA_WIDTH-1:0] data_out,
    input wire[5:0] tau,
    input wire reset,
    output reg ready,
    output reg [38:0] accumulator
);
    // índice en la sumatoria
    reg [WINDOW_SIZE_BITS-1:0] sum_index = 0;
    reg [WINDOW_SIZE_BITS-1:0] new_sum_index = 0;

    // flipflop registers
    reg requested_xj = 0;
    reg requested_xjtau = 0;
    reg fetched_xj = 0;
    reg fetched_xjtau = 0;
    reg waiting_xj = 0;
    reg waiting_xjtau = 0;
    reg [DATA_WIDTH-1:0] xj = 0;
    reg [DATA_WIDTH-1:0] xjtau = 0;

    reg [15:0] new_address = 0;
    reg new_ready = 0;
    reg new_requested_xj = 0;
    reg new_fetched_xj = 0;
    reg new_requested_xjtau = 0;
    reg new_fetched_xjtau = 0;
    reg new_waiting_xj = 0;
    reg new_waiting_xjtau = 0;
    reg [DATA_WIDTH-1:0] new_xj = 0;
    reg [DATA_WIDTH-1:0] new_xjtau = 0;

    reg [38:0] new_accumulator = 0;

    always @(posedge clk) begin
        if (reset) begin
            sum_index       <= 0;
            requested_xj    <= 0;
            requested_xjtau <= 0;
            fetched_xj      <= 0;
            fetched_xjtau   <= 0;
            accumulator     <= 0;
            ready           <= 0;
            xj              <= 0;
            xjtau           <= 0;
            waiting_xj      <= 0;
            waiting_xjtau   <= 0;
        end
        else begin
            sum_index       <= new_sum_index;
            requested_xj    <= new_requested_xj;
            requested_xjtau <= new_requested_xjtau;
            fetched_xj      <= new_fetched_xj;
            fetched_xjtau   <= new_fetched_xjtau;
            accumulator     <= new_accumulator;
            address         <= new_address;
            ready           <= new_ready;
            xj              <= new_xj;
            xjtau           <= new_xjtau;
            waiting_xj      <= new_waiting_xj;
            waiting_xjtau   <= new_waiting_xjtau;
        end
    end

    always @(*) begin
        // Init lhs ff
        new_sum_index       = sum_index;
        new_requested_xj    = requested_xj;
        new_requested_xjtau = requested_xjtau;
        new_fetched_xj      = fetched_xj;
        new_fetched_xjtau   = fetched_xjtau;
        new_accumulator     = accumulator;
        new_address         = address;
        new_ready           = ready;
        new_waiting_xj      = waiting_xj;
        new_waiting_xjtau   = waiting_xjtau;

        if (~ready) begin
            if (!requested_xj) begin
                new_address = initial_address + sum_index;
                new_requested_xj = 1'b1;
            end
            else if (requested_xj && !waiting_xj) begin
                new_waiting_xj = 1'b1;
            end
            else if (waiting_xj && !fetched_xj) begin
                new_xj = data_out;
                new_fetched_xj = 1'b1;
            end
            else if (!requested_xjtau) begin
                new_address = initial_address + sum_index + tau;
                new_requested_xjtau = 1'b1;
            end
            else if (requested_xjtau && !waiting_xjtau) begin
                new_waiting_xjtau = 1'b1;
            end
            else if (waiting_xjtau && !fetched_xjtau) begin
                new_xjtau = data_out;
                new_fetched_xjtau = 1'b1;
            end
            // Aca ya tengo xj y xjtau
            else if (fetched_xjtau) begin
                if (xj < xjtau) begin
                    new_accumulator = accumulator + ((xjtau - xj) * (xjtau - xj));
                end
                else begin
                    new_accumulator = accumulator + ((xj - xjtau) * (xj - xjtau));
                end

                // aumento y reseteo
                new_sum_index = sum_index + 1;
                new_requested_xj = 0;
                new_requested_xjtau = 0;
                new_fetched_xj = 0;
                new_fetched_xjtau = 0;
                new_waiting_xj = 0;
                new_waiting_xjtau = 0;
            end
            if (sum_index == (2 ** WINDOW_SIZE_BITS) - 1) begin
                new_ready = 1'b1;
                new_xj = 0;
                new_xjtau = 0;
            end
        end
    end

endmodule

diff_module_tb.v
`timescale 1ns/1ps

module diff_module_tb;

    parameter DATA_WIDTH_BITS = 16;
    parameter WINDOW_SIZE_BITS = 4; // 16 muestras (reducido para test rápido)
    parameter BUFFER_SIZE = 1 << WINDOW_SIZE_BITS;
    parameter MAX_TAU = 40; // representa 20ms

    reg clk = 1;
    always #5 clk = ~clk;  // Clock de 100MHz

    reg reset = 1;
    reg [15:0] initial_address = 0;
    reg [5:0] tau = 0;
    wire [15:0] address;
    wire ready;

    // Memoria simulada con BUFFER_SIZE entradas
    reg [DATA_WIDTH_BITS-1:0] memory [0:2*BUFFER_SIZE-1];

    // Salida actual del dato leído
    reg [DATA_WIDTH_BITS-1:0] data_out = 0;

    // Resultado de la funcion de diferencias
    reg [38:0] resultados [MAX_TAU];
    wire [38:0] resultado_diferencias;

    // Instancia del módulo
    diff_module #(
        .WINDOW_SIZE_BITS(WINDOW_SIZE_BITS),
        .DATA_WIDTH(DATA_WIDTH_BITS)
    ) dut (
        .clk(clk),
        .address(address),
        .initial_address(initial_address),
        .tau(tau),
        .reset(reset),
        .ready(ready),
        .data_out(data_out),
        .accumulator(resultado_diferencias)
    );

    initial begin
        // Inicializo memoria con algunos datos de prueba
        integer i;
        for (i = 1; i < 2*BUFFER_SIZE + 1; i = i + 1) begin
            memory[i-1] = i;  // Datos lineales: 0, 1, 2, ..., 31
        end
    end

    // Simula lectura de memoria
    always @(posedge clk) begin
        data_out <= memory[address];
    end
    
    reg total_ready = 0;
    reg detected = 0;
    reg delay = 0;
    always @(posedge clk) begin
        if (ready == 1 & ~detected) begin
            detected <= 1;
        end
        else if (ready == 1 & detected & ~delay) begin
            delay <= 1;
            tau <= tau + 1;
            reset <= 1;
        end
        else if (ready == 0) begin
            delay <= 0;
            reset <= 0;
        end
        if (tau > 3) begin
            reset <= 1;
            total_ready <= 1;
        end
    end

    initial begin
        // Dump de la simulación
        $dumpfile("waveform.vcd");
        $dumpvars(0, diff_module_tb);

        wait (total_ready == 1);
        #20 $finish;
    end

endmodule

waveform.vcd
$date
	Wed Jul 09 15:49:04 2025
$end
$version
	Icarus Verilog
$end
$timescale
	1ps
$end
$scope module diff_module_tb $end
$var wire 39 ! resultado_diferencias [38:0] $end
$var wire 1 " ready $end
$var wire 16 # address [15:0] $end
$var parameter 36 $ BUFFER_SIZE $end
$var parameter 32 % DATA_WIDTH_BITS $end
$var parameter 32 & MAX_TAU $end
$var parameter 32 ' WINDOW_SIZE_BITS $end
$var reg 1 ( clk $end
$var reg 16 ) data_out [15:0] $end
$var reg 1 * delay $end
$var reg 1 + detected $end
$var reg 16 , initial_address [15:0] $end
$var reg 1 - reset $end
$var reg 6 . tau [5:0] $end
$var reg 1 / total_ready $end
$scope module dut $end
$var wire 1 ( clk $end
$var wire 16 0 data_out [15:0] $end
$var wire 16 1 initial_address [15:0] $end
$var wire 1 - reset $end
$var wire 6 2 tau [5:0] $end
$var parameter 32 3 DATA_WIDTH $end
$var parameter 32 4 MAX_TAU $end
$var parameter 32 5 WINDOW_SIZE_BITS $end
$var reg 39 6 accumulator [38:0] $end
$var reg 16 7 address [15:0] $end
$var reg 1 8 fetched_xj $end
$var reg 1 9 fetched_xjtau $end
$var reg 39 : new_accumulator [38:0] $end
$var reg 16 ; new_address [15:0] $end
$var reg 1 < new_fetched_xj $end
$var reg 1 = new_fetched_xjtau $end
$var reg 1 > new_ready $end
$var reg 1 ? new_requested_xj $end
$var reg 1 @ new_requested_xjtau $end
$var reg 4 A new_sum_index [3:0] $end
$var reg 1 B new_waiting_xj $end
$var reg 1 C new_waiting_xjtau $end
$var reg 16 D new_xj [15:0] $end
$var reg 16 E new_xjtau [15:0] $end
$var reg 1 " ready $end
$var reg 1 F requested_xj $end
$var reg 1 G requested_xjtau $end
$var reg 4 H sum_index [3:0] $end
$var reg 1 I waiting_xj $end
$var reg 1 J waiting_xjtau $end
$var reg 16 K xj [15:0] $end
$var reg 16 L xjtau [15:0] $end
$upscope $end
$scope begin $unm_blk_1 $end
$var integer 32 M i [31:0] $end
$upscope $end
$upscope $end
$enddefinitions $end
$comment Show the parameter values. $end
$dumpall
b100 5
b101000 4
b10000 3
b100 '
b101000 &
b10000 %
b10000 $
$end
#0
$dumpvars
b100001 M
b0 L
b0 K
0J
0I
b0 H
0G
0F
b0 E
b0 D
0C
0B
b0 A
0@
0?
0>
0=
0<
b0 ;
b0 :
09
08
bx 7
bx 6
b0 2
b0 1
b0 0
0/
b0 .
1-
b0 ,
0+
0*
b0 )
1(
bx #
x"
bx !
$end
#5000
0(
#10000
1?
b0 ;
0"
b0 !
b0 6
bx )
bx 0
1(
#15000
0(
#20000
0-
1(
#25000
0(
#30000
1B
b0 #
b0 7
1F
1(
#35000
0(
#40000
1<
b1 D
b1 )
b1 0
1I
1(
#45000
0(
#50000
1@
b1 K
18
1(
#55000
0(
#60000
1C
1G
1(
#65000
0(
#70000
1=
b1 E
1J
1(
#75000
0(
#80000
0C
0B
0=
0<
0@
0?
b1 A
b1 L
19
1(
#85000
0(
#90000
1?
b1 ;
0J
0I
09
08
0G
0F
b1 H
1(
#95000
0(
#100000
1B
b1 #
b1 7
1F
1(
#105000
0(
#110000
1<
b10 D
1I
b10 )
b10 0
1(
#115000
0(
#120000
1@
b10 K
18
1(
#125000
0(
#130000
1C
1G
1(
#135000
0(
#140000
1=
b10 E
1J
1(
#145000
0(
#150000
0C
0B
0=
0<
0@
0?
b10 A
b10 L
19
1(
#155000
0(
#160000
1?
b10 ;
0J
0I
09
08
0G
0F
b10 H
1(
#165000
0(
#170000
1B
b10 #
b10 7
1F
1(
#175000
0(
#180000
1<
b11 D
b11 )
b11 0
1I
1(
#185000
0(
#190000
1@
b11 K
18
1(
#195000
0(
#200000
1C
1G
1(
#205000
0(
#210000
1=
b11 E
1J
1(
#215000
0(
#220000
0C
0B
0=
0<
0@
0?
b11 A
b11 L
19
1(
#225000
0(
#230000
1?
b11 ;
0J
0I
09
08
0G
0F
b11 H
1(
#235000
0(
#240000
1B
b11 #
b11 7
1F
1(
#245000
0(
#250000
1<
b100 D
1I
b100 )
b100 0
1(
#255000
0(
#260000
1@
b100 K
18
1(
#265000
0(
#270000
1C
1G
1(
#275000
0(
#280000
1=
b100 E
1J
1(
#285000
0(
#290000
0C
0B
0=
0<
0@
0?
b100 A
b100 L
19
1(
#295000
0(
#300000
1?
b100 ;
0J
0I
09
08
0G
0F
b100 H
1(
#305000
0(
#310000
1B
b100 #
b100 7
1F
1(
#315000
0(
#320000
1<
b101 D
b101 )
b101 0
1I
1(
#325000
0(
#330000
1@
b101 K
18
1(
#335000
0(
#340000
1C
1G
1(
#345000
0(
#350000
1=
b101 E
1J
1(
#355000
0(
#360000
0C
0B
0=
0<
0@
0?
b101 A
b101 L
19
1(
#365000
0(
#370000
1?
b101 ;
0J
0I
09
08
0G
0F
b101 H
1(
#375000
0(
#380000
1B
b101 #
b101 7
1F
1(
#385000
0(
#390000
1<
b110 D
1I
b110 )
b110 0
1(
#395000
0(
#400000
1@
b110 K
18
1(
#405000
0(
#410000
1C
1G
1(
#415000
0(
#420000
1=
b110 E
1J
1(
#425000
0(
#430000
0C
0B
0=
0<
0@
0?
b110 A
b110 L
19
1(
#435000
0(
#440000
1?
b110 ;
0J
0I
09
08
0G
0F
b110 H
1(
#445000
0(
#450000
1B
b110 #
b110 7
1F
1(
#455000
0(
#460000
1<
b111 D
b111 )
b111 0
1I
1(
#465000
0(
#470000
1@
b111 K
18
1(
#475000
0(
#480000
1C
1G
1(
#485000
0(
#490000
1=
b111 E
1J
1(
#495000
0(
#500000
0C
0B
0=
0<
0@
0?
b111 A
b111 L
19
1(
#505000
0(
#510000
1?
b111 ;
0J
0I
09
08
0G
0F
b111 H
1(
#515000
0(
#520000
1B
b111 #
b111 7
1F
1(
#525000
0(
#530000
1<
b1000 D
1I
b1000 )
b1000 0
1(
#535000
0(
#540000
1@
b1000 K
18
1(
#545000
0(
#550000
1C
1G
1(
#555000
0(
#560000
1=
b1000 E
1J
1(
#565000
0(
#570000
0C
0B
0=
0<
0@
0?
b1000 A
b1000 L
19
1(
#575000
0(
#580000
1?
b1000 ;
0J
0I
09
08
0G
0F
b1000 H
1(
#585000
0(
#590000
1B
b1000 #
b1000 7
1F
1(
#595000
0(
#600000
1<
b1001 D
b1001 )
b1001 0
1I
1(
#605000
0(
#610000
1@
b1001 K
18
1(
#615000
0(
#620000
1C
1G
1(
#625000
0(
#630000
1=
b1001 E
1J
1(
#635000
0(
#640000
0C
0B
0=
0<
0@
0?
b1001 A
b1001 L
19
1(
#645000
0(
#650000
1?
b1001 ;
0J
0I
09
08
0G
0F
b1001 H
1(
#655000
0(
#660000
1B
b1001 #
b1001 7
1F
1(
#665000
0(
#670000
1<
b1010 D
1I
b1010 )
b1010 0
1(
#675000
0(
#680000
1@
b1010 K
18
1(
#685000
0(
#690000
1C
1G
1(
#695000
0(
#700000
1=
b1010 E
1J
1(
#705000
0(
#710000
0C
0B
0=
0<
0@
0?
b1010 A
b1010 L
19
1(
#715000
0(
#720000
1?
b1010 ;
0J
0I
09
08
0G
0F
b1010 H
1(
#725000
0(
#730000
1B
b1010 #
b1010 7
1F
1(
#735000
0(
#740000
1<
b1011 D
b1011 )
b1011 0
1I
1(
#745000
0(
#750000
1@
b1011 K
18
1(
#755000
0(
#760000
1C
1G
1(
#765000
0(
#770000
1=
b1011 E
1J
1(
#775000
0(
#780000
0C
0B
0=
0<
0@
0?
b1011 A
b1011 L
19
1(
#785000
0(
#790000
1?
b1011 ;
0J
0I
09
08
0G
0F
b1011 H
1(
#795000
0(
#800000
1B
b1011 #
b1011 7
1F
1(
#805000
0(
#810000
1<
b1100 D
1I
b1100 )
b1100 0
1(
#815000
0(
#820000
1@
b1100 K
18
1(
#825000
0(
#830000
1C
1G
1(
#835000
0(
#840000
1=
b1100 E
1J
1(
#845000
0(
#850000
0C
0B
0=
0<
0@
0?
b1100 A
b1100 L
19
1(
#855000
0(
#860000
1?
b1100 ;
0J
0I
09
08
0G
0F
b1100 H
1(
#865000
0(
#870000
1B
b1100 #
b1100 7
1F
1(
#875000
0(
#880000
1<
b1101 D
b1101 )
b1101 0
1I
1(
#885000
0(
#890000
1@
b1101 K
18
1(
#895000
0(
#900000
1C
1G
1(
#905000
0(
#910000
1=
b1101 E
1J
1(
#915000
0(
#920000
0C
0B
0=
0<
0@
0?
b1101 A
b1101 L
19
1(
#925000
0(
#930000
1?
b1101 ;
0J
0I
09
08
0G
0F
b1101 H
1(
#935000
0(
#940000
1B
b1101 #
b1101 7
1F
1(
#945000
0(
#950000
1<
b1110 D
1I
b1110 )
b1110 0
1(
#955000
0(
#960000
1@
b1110 K
18
1(
#965000
0(
#970000
1C
1G
1(
#975000
0(
#980000
1=
b1110 E
1J
1(
#985000
0(
#990000
0C
0B
0=
0<
0@
0?
b1110 A
b1110 L
19
1(
#995000
0(
#1000000
1?
b1110 ;
0J
0I
09
08
0G
0F
b1110 H
1(
#1005000
0(
#1010000
1B
b1110 #
b1110 7
1F
1(
#1015000
0(
#1020000
1<
b1111 D
b1111 )
b1111 0
1I
1(
#1025000
0(
#1030000
1@
b1111 K
18
1(
#1035000
0(
#1040000
1C
1G
1(
#1045000
0(
#1050000
1=
b1111 E
1J
1(
#1055000
0(
#1060000
0C
0B
0=
0<
0@
0?
b1111 A
b1111 L
19
1(
#1065000
0(
#1070000
b0 E
b0 D
1>
1?
b1111 ;
0J
0I
09
08
0G
0F
b1111 H
1(
#1075000
0(
#1080000
b0 L
b0 K
1"
b1111 #
b1111 7
1F
1(
#1085000
0(
#1090000
b10000 )
b10000 0
1+
1(
#1095000
0(
#1100000
1-
b1 .
b1 2
1*
1(
#1105000
0(
#1110000
b0 ;
0>
1?
b0 A
0"
0F
b0 H
1(
#1115000
0(
#1120000
0-
0*
1(
#1125000
0(
#1130000
1B
b0 #
b0 7
1F
1(
#1135000
0(
#1140000
1<
b1 D
b1 )
b1 0
1I
1(
#1145000
0(
#1150000
1@
b1 ;
b1 K
18
1(
#1155000
0(
#1160000
1C
b1 #
b1 7
1G
1(
#1165000
0(
#1170000
1=
b10 E
1J
b10 )
b10 0
1(
#1175000
0(
#1180000
0C
0B
0=
0<
0@
0?
b1 A
b1 :
b10 L
19
1(
#1185000
0(
#1190000
1?
0J
0I
b1 !
b1 6
09
08
0G
0F
b1 H
1(
#1195000
0(
#1200000
1B
1F
1(
#1205000
0(
#1210000
1<
b10 D
1I
1(
#1215000
0(
#1220000
1@
b10 ;
b10 K
18
1(
#1225000
0(
#1230000
1C
b10 #
b10 7
1G
1(
#1235000
0(
#1240000
1=
b11 E
b11 )
b11 0
1J
1(
#1245000
0(
#1250000
0C
0B
0=
0<
0@
0?
b10 A
b10 :
b11 L
19
1(
#1255000
0(
#1260000
1?
0J
0I
b10 !
b10 6
09
08
0G
0F
b10 H
1(
#1265000
0(
#1270000
1B
1F
1(
#1275000
0(
#1280000
1<
b11 D
1I
1(
#1285000
0(
#1290000
1@
b11 ;
b11 K
18
1(
#1295000
0(
#1300000
1C
b11 #
b11 7
1G
1(
#1305000
0(
#1310000
1=
b100 E
1J
b100 )
b100 0
1(
#1315000
0(
#1320000
0C
0B
0=
0<
0@
0?
b11 A
b11 :
b100 L
19
1(
#1325000
0(
#1330000
1?
0J
0I
b11 !
b11 6
09
08
0G
0F
b11 H
1(
#1335000
0(
#1340000
1B
1F
1(
#1345000
0(
#1350000
1<
b100 D
1I
1(
#1355000
0(
#1360000
1@
b100 ;
b100 K
18
1(
#1365000
0(
#1370000
1C
b100 #
b100 7
1G
1(
#1375000
0(
#1380000
1=
b101 E
b101 )
b101 0
1J
1(
#1385000
0(
#1390000
0C
0B
0=
0<
0@
0?
b100 A
b100 :
b101 L
19
1(
#1395000
0(
#1400000
1?
0J
0I
b100 !
b100 6
09
08
0G
0F
b100 H
1(
#1405000
0(
#1410000
1B
1F
1(
#1415000
0(
#1420000
1<
b101 D
1I
1(
#1425000
0(
#1430000
1@
b101 ;
b101 K
18
1(
#1435000
0(
#1440000
1C
b101 #
b101 7
1G
1(
#1445000
0(
#1450000
1=
b110 E
1J
b110 )
b110 0
1(
#1455000
0(
#1460000
0C
0B
0=
0<
0@
0?
b101 A
b101 :
b110 L
19
1(
#1465000
0(
#1470000
1?
0J
0I
b101 !
b101 6
09
08
0G
0F
b101 H
1(
#1475000
0(
#1480000
1B
1F
1(
#1485000
0(
#1490000
1<
b110 D
1I
1(
#1495000
0(
#1500000
1@
b110 ;
b110 K
18
1(
#1505000
0(
#1510000
1C
b110 #
b110 7
1G
1(
#1515000
0(
#1520000
1=
b111 E
b111 )
b111 0
1J
1(
#1525000
0(
#1530000
0C
0B
0=
0<
0@
0?
b110 A
b110 :
b111 L
19
1(
#1535000
0(
#1540000
1?
0J
0I
b110 !
b110 6
09
08
0G
0F
b110 H
1(
#1545000
0(
#1550000
1B
1F
1(
#1555000
0(
#1560000
1<
b111 D
1I
1(
#1565000
0(
#1570000
1@
b111 ;
b111 K
18
1(
#1575000
0(
#1580000
1C
b111 #
b111 7
1G
1(
#1585000
0(
#1590000
1=
b1000 E
1J
b1000 )
b1000 0
1(
#1595000
0(
#1600000
0C
0B
0=
0<
0@
0?
b111 A
b111 :
b1000 L
19
1(
#1605000
0(
#1610000
1?
0J
0I
b111 !
b111 6
09
08
0G
0F
b111 H
1(
#1615000
0(
#1620000
1B
1F
1(
#1625000
0(
#1630000
1<
b1000 D
1I
1(
#1635000
0(
#1640000
1@
b1000 ;
b1000 K
18
1(
#1645000
0(
#1650000
1C
b1000 #
b1000 7
1G
1(
#1655000
0(
#1660000
1=
b1001 E
b1001 )
b1001 0
1J
1(
#1665000
0(
#1670000
0C
0B
0=
0<
0@
0?
b1000 A
b1000 :
b1001 L
19
1(
#1675000
0(
#1680000
1?
0J
0I
b1000 !
b1000 6
09
08
0G
0F
b1000 H
1(
#1685000
0(
#1690000
1B
1F
1(
#1695000
0(
#1700000
1<
b1001 D
1I
1(
#1705000
0(
#1710000
1@
b1001 ;
b1001 K
18
1(
#1715000
0(
#1720000
1C
b1001 #
b1001 7
1G
1(
#1725000
0(
#1730000
1=
b1010 E
1J
b1010 )
b1010 0
1(
#1735000
0(
#1740000
0C
0B
0=
0<
0@
0?
b1001 A
b1001 :
b1010 L
19
1(
#1745000
0(
#1750000
1?
0J
0I
b1001 !
b1001 6
09
08
0G
0F
b1001 H
1(
#1755000
0(
#1760000
1B
1F
1(
#1765000
0(
#1770000
1<
b1010 D
1I
1(
#1775000
0(
#1780000
1@
b1010 ;
b1010 K
18
1(
#1785000
0(
#1790000
1C
b1010 #
b1010 7
1G
1(
#1795000
0(
#1800000
1=
b1011 E
b1011 )
b1011 0
1J
1(
#1805000
0(
#1810000
0C
0B
0=
0<
0@
0?
b1010 A
b1010 :
b1011 L
19
1(
#1815000
0(
#1820000
1?
0J
0I
b1010 !
b1010 6
09
08
0G
0F
b1010 H
1(
#1825000
0(
#1830000
1B
1F
1(
#1835000
0(
#1840000
1<
b1011 D
1I
1(
#1845000
0(
#1850000
1@
b1011 ;
b1011 K
18
1(
#1855000
0(
#1860000
1C
b1011 #
b1011 7
1G
1(
#1865000
0(
#1870000
1=
b1100 E
1J
b1100 )
b1100 0
1(
#1875000
0(
#1880000
0C
0B
0=
0<
0@
0?
b1011 A
b1011 :
b1100 L
19
1(
#1885000
0(
#1890000
1?
0J
0I
b1011 !
b1011 6
09
08
0G
0F
b1011 H
1(
#1895000
0(
#1900000
1B
1F
1(
#1905000
0(
#1910000
1<
b1100 D
1I
1(
#1915000
0(
#1920000
1@
b1100 ;
b1100 K
18
1(
#1925000
0(
#1930000
1C
b1100 #
b1100 7
1G
1(
#1935000
0(
#1940000
1=
b1101 E
b1101 )
b1101 0
1J
1(
#1945000
0(
#1950000
0C
0B
0=
0<
0@
0?
b1100 A
b1100 :
b1101 L
19
1(
#1955000
0(
#1960000
1?
0J
0I
b1100 !
b1100 6
09
08
0G
0F
b1100 H
1(
#1965000
0(
#1970000
1B
1F
1(
#1975000
0(
#1980000
1<
b1101 D
1I
1(
#1985000
0(
#1990000
1@
b1101 ;
b1101 K
18
1(
#1995000
0(
#2000000
1C
b1101 #
b1101 7
1G
1(
#2005000
0(
#2010000
1=
b1110 E
1J
b1110 )
b1110 0
1(
#2015000
0(
#2020000
0C
0B
0=
0<
0@
0?
b1101 A
b1101 :
b1110 L
19
1(
#2025000
0(
#2030000
1?
0J
0I
b1101 !
b1101 6
09
08
0G
0F
b1101 H
1(
#2035000
0(
#2040000
1B
1F
1(
#2045000
0(
#2050000
1<
b1110 D
1I
1(
#2055000
0(
#2060000
1@
b1110 ;
b1110 K
18
1(
#2065000
0(
#2070000
1C
b1110 #
b1110 7
1G
1(
#2075000
0(
#2080000
1=
b1111 E
b1111 )
b1111 0
1J
1(
#2085000
0(
#2090000
0C
0B
0=
0<
0@
0?
b1110 A
b1110 :
b1111 L
19
1(
#2095000
0(
#2100000
1?
0J
0I
b1110 !
b1110 6
09
08
0G
0F
b1110 H
1(
#2105000
0(
#2110000
1B
1F
1(
#2115000
0(
#2120000
1<
b1111 D
1I
1(
#2125000
0(
#2130000
1@
b1111 ;
b1111 K
18
1(
#2135000
0(
#2140000
1C
b1111 #
b1111 7
1G
1(
#2145000
0(
#2150000
1=
b10000 E
1J
b10000 )
b10000 0
1(
#2155000
0(
#2160000
0C
0B
0=
0<
0@
0?
b1111 A
b1111 :
b10000 L
19
1(
#2165000
0(
#2170000
b0 E
b0 D
1>
1?
0J
0I
b1111 !
b1111 6
09
08
0G
0F
b1111 H
1(
#2175000
0(
#2180000
b0 L
b0 K
1"
1F
1(
#2185000
0(
#2190000
1-
b10 .
b10 2
1*
1(
#2195000
0(
#2200000
b0 ;
0>
b0 :
1?
b0 A
0"
b0 !
b0 6
0F
b0 H
1(
#2205000
0(
#2210000
0-
0*
1(
#2215000
0(
#2220000
1B
b0 #
b0 7
1F
1(
#2225000
0(
#2230000
1<
b1 D
1I
b1 )
b1 0
1(
#2235000
0(
#2240000
1@
b10 ;
b1 K
18
1(
#2245000
0(
#2250000
1C
b10 #
b10 7
1G
1(
#2255000
0(
#2260000
1=
b11 E
b11 )
b11 0
1J
1(
#2265000
0(
#2270000
0C
0B
0=
0<
0@
0?
b1 A
b100 :
b11 L
19
1(
#2275000
0(
#2280000
1?
b1 ;
0J
0I
b100 !
b100 6
09
08
0G
0F
b1 H
1(
#2285000
0(
#2290000
1B
b1 #
b1 7
1F
1(
#2295000
0(
#2300000
1<
b10 D
b10 )
b10 0
1I
1(
#2305000
0(
#2310000
1@
b11 ;
b10 K
18
1(
#2315000
0(
#2320000
1C
b11 #
b11 7
1G
1(
#2325000
0(
#2330000
1=
b100 E
1J
b100 )
b100 0
1(
#2335000
0(
#2340000
0C
0B
0=
0<
0@
0?
b10 A
b1000 :
b100 L
19
1(
#2345000
0(
#2350000
1?
b10 ;
0J
0I
b1000 !
b1000 6
09
08
0G
0F
b10 H
1(
#2355000
0(
#2360000
1B
b10 #
b10 7
1F
1(
#2365000
0(
#2370000
1<
b11 D
1I
b11 )
b11 0
1(
#2375000
0(
#2380000
1@
b100 ;
b11 K
18
1(
#2385000
0(
#2390000
1C
b100 #
b100 7
1G
1(
#2395000
0(
#2400000
1=
b101 E
b101 )
b101 0
1J
1(
#2405000
0(
#2410000
0C
0B
0=
0<
0@
0?
b11 A
b1100 :
b101 L
19
1(
#2415000
0(
#2420000
1?
b11 ;
0J
0I
b1100 !
b1100 6
09
08
0G
0F
b11 H
1(
#2425000
0(
#2430000
1B
b11 #
b11 7
1F
1(
#2435000
0(
#2440000
1<
b100 D
b100 )
b100 0
1I
1(
#2445000
0(
#2450000
1@
b101 ;
b100 K
18
1(
#2455000
0(
#2460000
1C
b101 #
b101 7
1G
1(
#2465000
0(
#2470000
1=
b110 E
1J
b110 )
b110 0
1(
#2475000
0(
#2480000
0C
0B
0=
0<
0@
0?
b100 A
b10000 :
b110 L
19
1(
#2485000
0(
#2490000
1?
b100 ;
0J
0I
b10000 !
b10000 6
09
08
0G
0F
b100 H
1(
#2495000
0(
#2500000
1B
b100 #
b100 7
1F
1(
#2505000
0(
#2510000
1<
b101 D
1I
b101 )
b101 0
1(
#2515000
0(
#2520000
1@
b110 ;
b101 K
18
1(
#2525000
0(
#2530000
1C
b110 #
b110 7
1G
1(
#2535000
0(
#2540000
1=
b111 E
b111 )
b111 0
1J
1(
#2545000
0(
#2550000
0C
0B
0=
0<
0@
0?
b101 A
b10100 :
b111 L
19
1(
#2555000
0(
#2560000
1?
b101 ;
0J
0I
b10100 !
b10100 6
09
08
0G
0F
b101 H
1(
#2565000
0(
#2570000
1B
b101 #
b101 7
1F
1(
#2575000
0(
#2580000
1<
b110 D
b110 )
b110 0
1I
1(
#2585000
0(
#2590000
1@
b111 ;
b110 K
18
1(
#2595000
0(
#2600000
1C
b111 #
b111 7
1G
1(
#2605000
0(
#2610000
1=
b1000 E
1J
b1000 )
b1000 0
1(
#2615000
0(
#2620000
0C
0B
0=
0<
0@
0?
b110 A
b11000 :
b1000 L
19
1(
#2625000
0(
#2630000
1?
b110 ;
0J
0I
b11000 !
b11000 6
09
08
0G
0F
b110 H
1(
#2635000
0(
#2640000
1B
b110 #
b110 7
1F
1(
#2645000
0(
#2650000
1<
b111 D
1I
b111 )
b111 0
1(
#2655000
0(
#2660000
1@
b1000 ;
b111 K
18
1(
#2665000
0(
#2670000
1C
b1000 #
b1000 7
1G
1(
#2675000
0(
#2680000
1=
b1001 E
b1001 )
b1001 0
1J
1(
#2685000
0(
#2690000
0C
0B
0=
0<
0@
0?
b111 A
b11100 :
b1001 L
19
1(
#2695000
0(
#2700000
1?
b111 ;
0J
0I
b11100 !
b11100 6
09
08
0G
0F
b111 H
1(
#2705000
0(
#2710000
1B
b111 #
b111 7
1F
1(
#2715000
0(
#2720000
1<
b1000 D
b1000 )
b1000 0
1I
1(
#2725000
0(
#2730000
1@
b1001 ;
b1000 K
18
1(
#2735000
0(
#2740000
1C
b1001 #
b1001 7
1G
1(
#2745000
0(
#2750000
1=
b1010 E
1J
b1010 )
b1010 0
1(
#2755000
0(
#2760000
0C
0B
0=
0<
0@
0?
b1000 A
b100000 :
b1010 L
19
1(
#2765000
0(
#2770000
1?
b1000 ;
0J
0I
b100000 !
b100000 6
09
08
0G
0F
b1000 H
1(
#2775000
0(
#2780000
1B
b1000 #
b1000 7
1F
1(
#2785000
0(
#2790000
1<
b1001 D
1I
b1001 )
b1001 0
1(
#2795000
0(
#2800000
1@
b1010 ;
b1001 K
18
1(
#2805000
0(
#2810000
1C
b1010 #
b1010 7
1G
1(
#2815000
0(
#2820000
1=
b1011 E
b1011 )
b1011 0
1J
1(
#2825000
0(
#2830000
0C
0B
0=
0<
0@
0?
b1001 A
b100100 :
b1011 L
19
1(
#2835000
0(
#2840000
1?
b1001 ;
0J
0I
b100100 !
b100100 6
09
08
0G
0F
b1001 H
1(
#2845000
0(
#2850000
1B
b1001 #
b1001 7
1F
1(
#2855000
0(
#2860000
1<
b1010 D
b1010 )
b1010 0
1I
1(
#2865000
0(
#2870000
1@
b1011 ;
b1010 K
18
1(
#2875000
0(
#2880000
1C
b1011 #
b1011 7
1G
1(
#2885000
0(
#2890000
1=
b1100 E
1J
b1100 )
b1100 0
1(
#2895000
0(
#2900000
0C
0B
0=
0<
0@
0?
b1010 A
b101000 :
b1100 L
19
1(
#2905000
0(
#2910000
1?
b1010 ;
0J
0I
b101000 !
b101000 6
09
08
0G
0F
b1010 H
1(
#2915000
0(
#2920000
1B
b1010 #
b1010 7
1F
1(
#2925000
0(
#2930000
1<
b1011 D
1I
b1011 )
b1011 0
1(
#2935000
0(
#2940000
1@
b1100 ;
b1011 K
18
1(
#2945000
0(
#2950000
1C
b1100 #
b1100 7
1G
1(
#2955000
0(
#2960000
1=
b1101 E
b1101 )
b1101 0
1J
1(
#2965000
0(
#2970000
0C
0B
0=
0<
0@
0?
b1011 A
b101100 :
b1101 L
19
1(
#2975000
0(
